anybin2wheel/__init__.py
anybin2wheel/__main__.py
anybin2wheel-0.1.0.dist-info/METADATA
anybin2wheel-0.1.0.dist-info/WHEEL
anybin2wheel-0.1.0.dist-info/entry_points.txt
anybin2wheel-0.1.0.dist-info/top_level.txt
anybin2wheel-0.1.0.dist-info/RECORD
