Metadata-Version: 2.1
Name: anybin2wheel
Version: 0.1.0
Summary: Package any executable to be distributed as a wheel.
Author-email: Sergey Kolosov <m17.admin@gmail.com>
License: MIT
Project-URL: Homepage, https://github.com/sergeykolosov/anybin2wheel
Requires-Python: >=3.8
Requires-Dist: distlib >=0.3.8
